[
  {
    "class": "Class One",
    "students": [
      {
        "id": 1,
        "name": "Talha",
        "scores": "A+",
        "percentage": "98%",
        "image": "https://res.cloudinary.com/dxiygdbvg/image/upload/v1705430083/avatar_v45fsg.png"
      },
      {
        "id": 2,
        "name": "Sara",
        "scores": "A",
        "percentage": "92%",
        "image": "https://res.cloudinary.com/dxiygdbvg/image/upload/v1705430083/avatar_v45fsg.png"
      },
      {
        "id": 3,
        "name": "Ali",
        "scores": "B",
        "percentage": "85%",
        "image": "https://res.cloudinary.com/dxiygdbvg/image/upload/v1705430083/avatar_v45fsg.png"
      },
      {
        "id": 4,
        "name": "Aisha",
        "scores": "A+",
        "percentage": "95%",
        "image": "https://res.cloudinary.com/dxiygdbvg/image/upload/v1705430083/avatar_v45fsg.png"
      },
      {
        "id": 5,
        "name": "Zain",
        "scores": "A",
        "percentage": "90%",
        "image": "https://res.cloudinary.com/dxiygdbvg/image/upload/v1705430083/avatar_v45fsg.png"
      },
      {
        "id": 6,
        "name": "Fatima",
        "scores": "A+",
        "percentage": "97%",
        "image": "https://res.cloudinary.com/dxiygdbvg/image/upload/v1705430083/avatar_v45fsg.png"
      },
      {
        "id": 7,
        "name": "Ahmed",
        "scores": "B+",
        "percentage": "88%",
        "image": "https://res.cloudinary.com/dxiygdbvg/image/upload/v1705430083/avatar_v45fsg.png"
      },
      {
        "id": 8,
        "name": "Zara",
        "scores": "A+",
        "percentage": "96%",
        "image": "https://res.cloudinary.com/dxiygdbvg/image/upload/v1705430083/avatar_v45fsg.png"
      },
      {
        "id": 9,
        "name": "Khalid",
        "scores": "A",
        "percentage": "93%",
        "image": "https://res.cloudinary.com/dxiygdbvg/image/upload/v1705430083/avatar_v45fsg.png"
      },
      {
        "id": 10,
        "name": "Nida",
        "scores": "A+",
        "percentage": "99%",
        "image": "https://res.cloudinary.com/dxiygdbvg/image/upload/v1705430083/avatar_v45fsg.png"
      }
    ]
  },
  {
    "class": "Class Two",
    "students": [
      {
        "id": 1,
        "name": "Abir",
        "scores": "A+",
        "percentage": "98%",
        "image": "https://res.cloudinary.com/dxiygdbvg/image/upload/v1705430083/avatar_v45fsg.png"
      },
      {
        "id": 2,
        "name": "Sophia",
        "scores": "B+",
        "percentage": "85%",
        "image": "https://res.cloudinary.com/dxiygdbvg/image/upload/v1705430083/avatar_v45fsg.png"
      },
      {
        "id": 3,
        "name": "Ryan",
        "scores": "A",
        "percentage": "92%",
        "image": "https://res.cloudinary.com/dxiygdbvg/image/upload/v1705430083/avatar_v45fsg.png"
      },
      {
        "id": 4,
        "name": "Ella",
        "scores": "A+",
        "percentage": "95%",
        "image": "https://res.cloudinary.com/dxiygdbvg/image/upload/v1705430083/avatar_v45fsg.png"
      },
      {
        "id": 5,
        "name": "Mia",
        "scores": "A",
        "percentage": "90%",
        "image": "https://res.cloudinary.com/dxiygdbvg/image/upload/v1705430083/avatar_v45fsg.png"
      },
      {
        "id": 6,
        "name": "Noah",
        "scores": "A+",
        "percentage": "97%",
        "image": "https://res.cloudinary.com/dxiygdbvg/image/upload/v1705430083/avatar_v45fsg.png"
      },
      {
        "id": 7,
        "name": "Emma",
        "scores": "B+",
        "percentage": "88%",
        "image": "https://res.cloudinary.com/dxiygdbvg/image/upload/v1705430083/avatar_v45fsg.png"
      },
      {
        "id": 8,
        "name": "Olivia",
        "scores": "A+",
        "percentage": "96%",
        "image": "https://res.cloudinary.com/dxiygdbvg/image/upload/v1705430083/avatar_v45fsg.png"
      },
      {
        "id": 9,
        "name": "Liam",
        "scores": "A",
        "percentage": "93%",
        "image": "https://res.cloudinary.com/dxiygdbvg/image/upload/v1705430083/avatar_v45fsg.png"
      },
      {
        "id": 10,
        "name": "Ava",
        "scores": "A+",
        "percentage": "99%",
        "image": "https://res.cloudinary.com/dxiygdbvg/image/upload/v1705430083/avatar_v45fsg.png"
      }
    ]
  }
]
